pop_archive/conf.py
pop_archive/version.py
pop_archive/exec/tar.py
pop_archive-0.1.0.dist-info/LICENSE
pop_archive-0.1.0.dist-info/METADATA
pop_archive-0.1.0.dist-info/WHEEL
pop_archive-0.1.0.dist-info/entry_points.txt
pop_archive-0.1.0.dist-info/top_level.txt
pop_archive-0.1.0.dist-info/RECORD
